{
    "no_wrap": true,
    "text_block_list": [
        {
            "name": "Hayakawa Tazuna",
            "text": "Itu balapan yang hebat…! \nMembuatku benar-benar terbakar semangatnya!!"
        },
        {
            "name": "Hayakawa Tazuna",
            "text": "Sekarang setelah balapan selesai… \nsaatnya untuk Winning Live!",
            "color_text_info_list": [
                "Winning Live"
            ]
        },
        {
            "name": "Hayakawa Tazuna",
            "text": "Winning Live… ini adalah tempat di mana \npara pemenang Uma Musume dan para penggemar yang \nbersorak-sorai dapat berbagi kebahagiaan mereka!"
        },
        {
            "name": "Hayakawa Tazuna",
            "text": "Posisi tengah, tempat di mana hanya juara pertama yang \ndapat berdiri, adalah tujuan yang dikejar oleh semuanya."
        },
        {
            "name": "Hayakawa Tazuna",
            "text": "Ada lagu-lagu yang hanya bisa dinyanyikan \njika kamu memenangkan balapan khusus, atau \njika kamu mencapai prestasi besar."
        },
        {
            "name": "Hayakawa Tazuna",
            "text": "Perasaan yang Anda lihat sangat mengharukan."
        },
        {
            "name": "Hayakawa Tazuna",
            "text": "Selain itu, banyak orang yang menjadi \npenggemar para Uma Musume setelah \nmenonton penampilan live mereka."
        },
        {
            "name": "Hayakawa Tazuna",
            "text": "Winning Live adalah elemen yang tak tergantikan \nbagi para Uma Musume!"
        },
        {
            "name": "Hayakawa Tazuna",
            "text": "Sekarang, mari kita lihat para Uma Musume \nberkilau di atas panggung!"
        }
    ]
}
